<?xml version="1.0"?>
<extensions>
	<details>
		<title lang="EN">Remote Home Assistant</title>
	</details>	
	<plugins>
		<plugin name="Assistant" version="0.4" minTarget="7.6" maxTarget="*">
			<title lang="EN">Assistant</title>
			<desc lang="EN">Remote controlling entities in Home Assistant.</desc>
			<creator>Hans Karlinius</creator>
			<email>hans.karlinius@live.com</email>
			<url>https://hans99.github.io/slim/Assistant-0.4.zip</url>
			<sha>fb7b00cd15e3d02c46133987c749aa5b7ff30ce2</sha>
		</plugin>
	</plugins>
</extensions>
